logseq_py/__init__.py
logseq_py/cli.py
logseq_py/logseq_client.py
logseq_py/models.py
logseq_py/query.py
logseq_py/utils.py
logseq_py/builders/__init__.py
logseq_py/builders/advanced_builders.py
logseq_py/builders/content_types.py
logseq_py/builders/core.py
logseq_py/builders/page_builders.py
logseq_py/builders/parser.py
logseq_py/pipeline/__init__.py
logseq_py/pipeline/analyzers.py
logseq_py/pipeline/async_comprehensive_processor.py
logseq_py/pipeline/async_core.py
logseq_py/pipeline/async_queue.py
logseq_py/pipeline/cache.py
logseq_py/pipeline/comprehensive_processor.py
logseq_py/pipeline/core.py
logseq_py/pipeline/enhanced_extractors.py
logseq_py/pipeline/extractors.py
logseq_py/pipeline/filters.py
logseq_py/pipeline/generators.py
logseq_py/pipeline/steps.py
logseq_py/pipeline/subtitle_extractor.py
logseq_py/pipeline/video_processor.py
logseq_python-0.2.1.dist-info/licenses/LICENSE
logseq_python-0.2.1.dist-info/METADATA
logseq_python-0.2.1.dist-info/WHEEL
logseq_python-0.2.1.dist-info/entry_points.txt
logseq_python-0.2.1.dist-info/top_level.txt
logseq_python-0.2.1.dist-info/RECORD
