Metadata-Version: 2.4
Name: logseq-python
Version: 0.2.1
Summary: A comprehensive Python library for working with Logseq knowledge graphs
Home-page: https://github.com/thinmanj/logseq-python-library
Author: Julio Ona
Author-email: Julio Ona <thinmanj@gmail.com>
License: MIT
Project-URL: Homepage, https://github.com/thinmanj/logseq-python-library
Project-URL: Documentation, https://github.com/thinmanj/logseq-python-library#readme
Project-URL: Repository, https://github.com/thinmanj/logseq-python-library
Project-URL: Bug Tracker, https://github.com/thinmanj/logseq-python-library/issues
Keywords: logseq,knowledge-graph,note-taking,markdown,pipeline
Classifier: Development Status :: 3 - Alpha
Classifier: Intended Audience :: Developers
Classifier: License :: OSI Approved :: MIT License
Classifier: Operating System :: OS Independent
Classifier: Programming Language :: Python :: 3
Classifier: Programming Language :: Python :: 3.8
Classifier: Programming Language :: Python :: 3.9
Classifier: Programming Language :: Python :: 3.10
Classifier: Programming Language :: Python :: 3.11
Classifier: Programming Language :: Python :: 3.12
Classifier: Topic :: Software Development :: Libraries :: Python Modules
Classifier: Topic :: Text Processing :: Markup
Classifier: Topic :: Office/Business :: Groupware
Requires-Python: >=3.8
License-File: LICENSE
Requires-Dist: requests>=2.25.0
Requires-Dist: beautifulsoup4>=4.9.0
Requires-Dist: lxml>=4.6.0
Requires-Dist: python-dateutil>=2.8.0
Requires-Dist: pyyaml>=6.0
Requires-Dist: regex>=2021.4.4
Requires-Dist: markdown>=3.3.0
Provides-Extra: dev
Requires-Dist: pytest>=7.0.0; extra == "dev"
Requires-Dist: pytest-cov>=4.0.0; extra == "dev"
Requires-Dist: pytest-asyncio>=0.21.0; extra == "dev"
Requires-Dist: pytest-mock>=3.10.0; extra == "dev"
Requires-Dist: black>=23.0.0; extra == "dev"
Requires-Dist: flake8>=6.0.0; extra == "dev"
Requires-Dist: mypy>=1.0.0; extra == "dev"
Requires-Dist: isort>=5.12.0; extra == "dev"
Provides-Extra: test
Requires-Dist: pytest>=7.0.0; extra == "test"
Requires-Dist: pytest-cov>=4.0.0; extra == "test"
Requires-Dist: pytest-asyncio>=0.21.0; extra == "test"
Requires-Dist: pytest-mock>=3.10.0; extra == "test"
Provides-Extra: cli
Requires-Dist: click>=8.0.0; extra == "cli"
Requires-Dist: rich>=13.0.0; extra == "cli"
Requires-Dist: typer>=0.9.0; extra == "cli"
Provides-Extra: pipeline
Requires-Dist: click>=8.0.0; extra == "pipeline"
Requires-Dist: rich>=13.0.0; extra == "pipeline"
Requires-Dist: regex>=2021.4.4; extra == "pipeline"
Requires-Dist: markdown>=3.3.0; extra == "pipeline"
Provides-Extra: ml
Requires-Dist: scikit-learn>=1.2.0; extra == "ml"
Requires-Dist: numpy>=1.21.0; extra == "ml"
Requires-Dist: pandas>=1.5.0; extra == "ml"
Dynamic: author
Dynamic: home-page
Dynamic: license-file
Dynamic: requires-python
